PVRTexLib.dll
_igeCore.cp39-win_amd64.pyd
libfbxsdk.dll
igeCore/__init__.py
igeCore/apputil/__init__.py
igeCore/apputil/graphicsHelper.py
igeCore/apputil/imguirenderer.py
igeCore/apputil/launch_server.py
igeCore/devtool/__init__.py
igeCore/input/__init__.py
igeCore/input/keyboard.py
igeCore/input/touch.py
igeCore-0.6.3.dist-info/LICENSE
igeCore-0.6.3.dist-info/METADATA
igeCore-0.6.3.dist-info/WHEEL
igeCore-0.6.3.dist-info/top_level.txt
igeCore-0.6.3.dist-info/RECORD
