Metadata-Version: 2.1
Name: igeCore
Version: 0.6.3
Summary: Indi Games Engine core module
Home-page: https://indigames.net/
Author: Indigames
Author-email: dev@indigames.net
License: MIT
Platform: UNKNOWN
Classifier: Intended Audience :: Developers
Classifier: License :: OSI Approved :: MIT License
Classifier: Programming Language :: Python :: 3
Classifier: Operating System :: Microsoft :: Windows
Classifier: Topic :: Games/Entertainment
License-File: LICENSE
Requires-Dist: igeVmath
Requires-Dist: requests
